pycolbertdb/__init__.py
pycolbertdb/client.py
pycolbertdb/helpers.py
pycolbertdb/models.py
pycolbertdb-0.2.8.dist-info/LICENSE
pycolbertdb-0.2.8.dist-info/METADATA
pycolbertdb-0.2.8.dist-info/WHEEL
pycolbertdb-0.2.8.dist-info/RECORD
