Metadata-Version: 2.1
Name: pycolbertdb
Version: 0.2.8
Summary: Python client for colbertdb
License: MIT
Author: Ryan Sloan
Author-email: rysloan4@gmail.com
Requires-Python: >=3.12,<4.0
Classifier: License :: OSI Approved :: MIT License
Classifier: Programming Language :: Python :: 3
Classifier: Programming Language :: Python :: 3.12
Requires-Dist: datamodel-code-generator[http] (>=0.25.6,<0.26.0)
Requires-Dist: llama-index-readers-web (>=0.1.14,<0.2.0)
Requires-Dist: pytest (>=8.2.0,<9.0.0)
Requires-Dist: requests (>=2.32.0,<3.0.0)
